studioai/__init__.py
studioai/analysis/__init__.py
studioai/analysis/container.py
studioai/analysis/explore/__init__.py
studioai/analysis/explore/eda.py
studioai/analysis/explore/example.py
studioai/analysis/stats/__init__.py
studioai/analysis/stats/descriptive/__init__.py
studioai/analysis/stats/descriptive/base.py
studioai/analysis/stats/descriptive/categorical.py
studioai/analysis/stats/descriptive/continuous.py
studioai/analysis/stats/descriptive/summary.py
studioai/analysis/stats/distribution/__init__.py
studioai/analysis/stats/distribution/generate.py
studioai/analysis/stats/inferential/__init__.py
studioai/analysis/stats/inferential/association.py
studioai/analysis/stats/inferential/base.py
studioai/analysis/stats/inferential/centrality.py
studioai/analysis/stats/inferential/correlation.py
studioai/analysis/stats/inferential/gof.py
studioai/analysis/stats/inferential/independence.py
studioai/analysis/stats/inferential/profile.py
studioai/analysis/stats/inferential/test.py
studioai/analysis/visualize/__init__.py
studioai/analysis/visualize/base.py
studioai/analysis/visualize/visualizer.py
studioai/data/__init__.py
studioai/data/dataset.py
studioai/preprocessing/__init__.py
studioai/preprocessing/base.py
studioai/preprocessing/encode.py
studioai/py.typed
studioai/util/__init__.py
studioai/util/io.py
studioai/util/string.py
studioai-0.2.24.dist-info/WHEEL
studioai-0.2.24.dist-info/METADATA
studioai-0.2.24.dist-info/RECORD
